Multiplexadores_TesteBench/mux1.vhdl
-- Autor: Caellison Bezerra Morais
-- Data: 29/11/2024
-- Multiplexador de 4 entradas e 1 saida

-- Biblioteca IEEE

      library ieee;
      use ieee.std_logic_1164.all;

-- Declaracao das variaveis de entrada e saida 

      entity mux1 is
      port (

      I0 : in std_logic;  -- Entrada de dados 0
      I1 : in std_logic;  -- Entrada de dados 1
      I2 : in std_logic;  -- Entrada de dados 2
      I3 : in std_logic;  -- Entrada de dados 3
      s  : in std_logic_vector (1 downto 0);  -- Seleção de Entradas (S1,S0)
      y  : out std_logic  -- Saida

           );
       end mux1;


-- Arquitetura do muxtiplexador com logica sequencial

     architecture arch of mux1 is 
     begin 
                 process(I0, I1, I2, I3, s)
                 begin
                 case s is

                 when "00" => y <= I0;  -- Seleciona I0
                 when "01" => y <= I1;  -- Seleciona I1
                 when "10" => y <= I2;  -- Seleciona I2
                 when "11" => y <= I3;  -- Seleciona I3
                 when others => y <= '0';              -- Garante o valor 0 para nenhuma das entradas
                 end case;
                 end process;
     end arch;

Multiplexadores_TesteBench/testemux.vhdl
-- Autor: Caellison Bezerra Morais 
-- Data: 30/11/2024
-- TesteBench para Multiplexadores de 4 entradas e 1 saida

-- Biblioteca IEEE

   library ieee;
   use ieee.std_logic_1164.all;
   use ieee.numeric_std.all;

   entity testemux is
   end testemux;

-- Arquitetura do testebench

	architecture arch of testemux is 

-- Componente a ser testada ( troque 'mux1' por 'mux2' ou 'mux...')
 	component mux1 
	port(
		I0, I1, I2, I3 : in std_logic;
		s	       : in std_logic_vector (1 downto 0);
		y	       : out std_logic
	);
	end component;

-- Sinais para simulacao

	signal I0, I1, I2, I3 : std_logic := '0' ; 
	signal s	      : std_logic_vector(1 downto 0) := "00";
	signal y	      : std_logic;

begin

-- Instaciacao do multiplexador ( trocar 'mux1' pelo nome do multiplexador desejado )

	uut1: mux1 port map(I0, I1, I2, I3, s, y);

-- Processo de geração de dados
	process
	begin 

--Testando todas combinacoes de selecao
	
	for i in 0 to 3 loop
	s <= std_logic_vector(to_unsigned(i, 2));   -- converscao para sinais de selecao ajustada

	I0 <= '0';  I1 <= '1';  I2 <= '0';  I3 <= '1' ; wait for 10 ns;

	wait for 10 ns;

	--Reinicia as entradas para as diferentes combinacoes de selecao
	I0 <= '1';  I1 <= '0';  I2 <= '1';  I3 <= '1'; wait for 10 ns;
end loop;

	wait; --Finaliza simulacao
end process;
end arch;

Multiplexadores_TesteBench/testemux.vcd
$date
  Fri Dec  6 14:47:54 2024
$end
$version
  GHDL v0
$end
$timescale
  1 fs
$end
$scope module standard $end
$upscope $end
$scope module std_logic_1164 $end
$upscope $end
$scope module numeric_std $end
$upscope $end
$scope module testemux $end
$var reg 1 ! i0 $end
$var reg 1 " i1 $end
$var reg 1 # i2 $end
$var reg 1 $ i3 $end
$var reg 2 % s[1:0] $end
$var reg 1 & y $end
$scope module uut1 $end
$var reg 1 ' i0 $end
$var reg 1 ( i1 $end
$var reg 1 ) i2 $end
$var reg 1 * i3 $end
$var reg 2 + s[1:0] $end
$var reg 1 , y $end
$upscope $end
$upscope $end
$enddefinitions $end
#0
0!
1"
0#
1$
b00 %
0&
0'
1(
0)
1*
b00 +
0,
#10000000
#20000000
1!
0"
1#
1&
1'
0(
1)
1,
#30000000
0!
1"
0#
b01 %
0'
1(
0)
b01 +
#40000000
#50000000
1!
0"
1#
0&
1'
0(
1)
0,
#60000000
0!
1"
0#
b10 %
0'
1(
0)
b10 +
#70000000
#80000000
1!
0"
1#
1&
1'
0(
1)
1,
#90000000
0!
1"
0#
b11 %
0'
1(
0)
b11 +
#100000000
#110000000
1!
0"
1#
1'
0(
1)
